{
  "type": "create:compacting",
  "ingredients": [
    {
      "item": "minecraft:bone_meal"
    },
    {
      "item": "minecraft:bone_meal"
    },
    {
      "item": "minecraft:bone_meal"
    },
    {
      "item": "minecraft:bone_meal"
    },
    {
      "item": "minecraft:bone_meal"
    },
    {
      "item": "minecraft:bone_meal"
    },
    {
      "item": "minecraft:bone_meal"
    },
    {
      "item": "minecraft:bone_meal"
    },
    {
      "item": "minecraft:bone_meal"
    },
    {
      "tag": "tfc:mortar"
    }
  ],
  "results": [
    {
      "item": "minecraft:bone_block"
    }
  ]
}