{
  "type": "tfc:damage_inputs_shapeless_crafting",
  "recipe": {
    "type": "tfc:advanced_shapeless_crafting",
    "ingredients": [
      {
        "type": "tfc:not_rotten",
        "ingredient": {
          "item": "tfc:food/oat_bread"
        }
      },
      {
        "tag": "tfc:knives"
      }
    ],
    "primary_ingredient": {
      "item": "tfc:food/oat_bread"
    },
    "result": {
      "stack": {
        "item": "firmalife:food/oat_slice",
        "count": 2
      },
      "modifiers": [
        "tfc:copy_food"
      ]
    }
  }
}