{
    "__comment__": "generated by air!",
    "type": "mekanism:painting",
    "itemInput": {
        "ingredient": {
            "type": "forge:difference",
            "base": {
                "tag": "tfc:colored_shulker_boxes"
            },
            "subtracted": {
                "item": "minecraft:cyan_shulker_box"
            }
        }
    },
    "chemicalInput": {
        "amount": 8,
        "pigment": "mekanism:cyan"
    },
    "output": {
        "item": "minecraft:cyan_shulker_box"
    }
}
